my_new_code/init.py
my_new_code-0.1.dist-info/METADATA
my_new_code-0.1.dist-info/WHEEL
my_new_code-0.1.dist-info/top_level.txt
my_new_code-0.1.dist-info/RECORD
