Metadata-Version: 2.1
Name: my-new-code
Version: 0.1
Summary: this is a package
Home-page: UNKNOWN
Author: Sir Qasim and Syed Muhammad Mooazam
License: UNKNOWN
Platform: UNKNOWN
